odoo/addons/product_product_sale_subscription_template/CHANGELOG.md
odoo/addons/product_product_sale_subscription_template/README.rst
odoo/addons/product_product_sale_subscription_template/__init__.py
odoo/addons/product_product_sale_subscription_template/__manifest__.py
odoo/addons/product_product_sale_subscription_template/hooks.py
odoo/addons/product_product_sale_subscription_template/listeners/__init__.py
odoo/addons/product_product_sale_subscription_template/listeners/contract_line_listener.py
odoo/addons/product_product_sale_subscription_template/models/__init__.py
odoo/addons/product_product_sale_subscription_template/models/product_product.py
odoo/addons/product_product_sale_subscription_template/tests/__init__.py
odoo/addons/product_product_sale_subscription_template/tests/listeners/__init__.py
odoo/addons/product_product_sale_subscription_template/tests/listeners/test_contract_line_listener.py
odoo/addons/product_product_sale_subscription_template/views/product_views.xml
odoo_addon_product_product_sale_subscription_template-16.0.1.0.1.dist-info/METADATA
odoo_addon_product_product_sale_subscription_template-16.0.1.0.1.dist-info/WHEEL
odoo_addon_product_product_sale_subscription_template-16.0.1.0.1.dist-info/top_level.txt
odoo_addon_product_product_sale_subscription_template-16.0.1.0.1.dist-info/RECORD
