Metadata-Version: 2.1
Name: odoo-addon-product-product-sale-subscription-template
Version: 16.0.1.0.1
Summary: Sets a basic structure for multimedia subscriptions within the SomConnexio ERP
Home-page: https://coopdevs.org
Author: Coopdevs Treball SCCL, Som Connexió SCCL
License: AGPL-3
Platform: UNKNOWN
Classifier: Programming Language :: Python
Classifier: Framework :: Odoo
Classifier: Framework :: Odoo :: 16.0
Classifier: License :: OSI Approved :: GNU Affero General Public License v3
Requires-Python: >=3.10
Requires-Dist: odoo-addon-somconnexio <16.1dev,>=16.0dev
Requires-Dist: odoo-addon-subscription-oca <16.1dev,>=16.0dev
Requires-Dist: odoo <16.1dev,>=16.0a
